pretix_banktransferfi/__init__.py
pretix_banktransferfi/payment.py
pretix_banktransferfi/signals.py
pretix_banktransferfi/viitenumero.py
pretix_banktransferfi/templates/pretix_banktransferfi/checkout_payment_form.html
pretix_banktransferfi/templates/pretix_banktransferfi/control.html
pretix_banktransferfi/templates/pretix_banktransferfi/pending.html
pretix_banktransferfi/templates/pretix_banktransferfi/email/order_pending.txt
pretix_banktransferfi-1.0.2.dist-info/LICENSE.txt
pretix_banktransferfi-1.0.2.dist-info/METADATA
pretix_banktransferfi-1.0.2.dist-info/RECORD
pretix_banktransferfi-1.0.2.dist-info/WHEEL
pretix_banktransferfi-1.0.2.dist-info/entry_points.txt
pretix_banktransferfi-1.0.2.dist-info/top_level.txt
