Metadata-Version: 2.1
Name: pretix-banktransferfi
Version: 1.0.2
Summary: Pretix plugin that creates a reference number (viitenumero) compliant with Finnish banks.
Home-page: https://github.com/fmorato/pretix-banktransferfi
Author: Felipe Morato
Author-email: me@fmorato.com
License: Apache Software License
Platform: UNKNOWN
